crawlab_ai/__init__.py
crawlab_ai/cli/__init__.py
crawlab_ai/cli/codegen.py
crawlab_ai/cli/config.py
crawlab_ai/cli/crawl.py
crawlab_ai/code/__init__.py
crawlab_ai/code/article.py
crawlab_ai/code/list.py
crawlab_ai/scrapy/__init__.py
crawlab_ai/scrapy/base.py
crawlab_ai/scrapy/list_spider.py
crawlab_ai/spider/__init__.py
crawlab_ai/spider/article_spider.py
crawlab_ai/spider/base.py
crawlab_ai/spider/list_spider.py
crawlab_ai/utils/__init__.py
crawlab_ai/utils/auth.py
crawlab_ai/utils/env.py
crawlab_ai/utils/logger.py
test/__init__.py
test/utils/__init__.py
test/utils/test_auth.py
crawlab_ai-0.0.10.dist-info/LICENSE
crawlab_ai-0.0.10.dist-info/METADATA
crawlab_ai-0.0.10.dist-info/WHEEL
crawlab_ai-0.0.10.dist-info/entry_points.txt
crawlab_ai-0.0.10.dist-info/top_level.txt
crawlab_ai-0.0.10.dist-info/RECORD
