Metadata-Version: 2.1
Name: crawlab-ai
Version: 0.0.10
Summary: SDK for Crawlab AI
Home-page: https://github.com/crawlab-team/crawlab-ai-sdk
Author: Marvin Zhang
Author-email: tikazyq@163.com
License: MIT
Keywords: crawlab,ai
License-File: LICENSE
Requires-Dist: Scrapy >=2.4
Requires-Dist: requests ~=2.31.0
Requires-Dist: pytest >=8.0.0
Requires-Dist: pandas >=2.2
Requires-Dist: bs4 ==0.0.2
Requires-Dist: black ==24.3.0
Requires-Dist: tabulate ==0.9.0
